README.md
setup.py
Displaycontrol.egg-info/PKG-INFO
Displaycontrol.egg-info/SOURCES.txt
Displaycontrol.egg-info/dependency_links.txt
Displaycontrol.egg-info/top_level.txt
displaycontrol/__init__.py
displaycontrol/displaycontrol.py
displaycontrol/exceptions.py
displaycontrol/tools.py