Metadata-Version: 1.1
Name: Displaycontrol
Version: 0.0.2
Summary: Package to control displays and projectors via serial and ethernet connection.
Home-page: https://github.com/TopRedMedia/displaycontrol
Author: Mirko Haaser
Author-email: mirko@topred.media
License: Creative Commons Attribution-Noncommercial-Share Alike license
Platform: UNKNOWN
Classifier: Development Status :: 3 - Alpha
Classifier: Intended Audience :: Developers
Classifier: Topic :: System :: Hardware
Classifier: License :: OSI Approved :: MIT License
Classifier: Programming Language :: Python :: 2.7
